certifi/__init__.py
certifi/__main__.py
certifi/cacert.pem
certifi/core.py
certifi/py.typed
charset_normalizer/__init__.py
charset_normalizer/__main__.py
charset_normalizer/api.py
charset_normalizer/cd.py
charset_normalizer/constant.py
charset_normalizer/legacy.py
charset_normalizer/md.cpython-310-aarch64-linux-gnu.so
charset_normalizer/md.cpython-310-x86_64-linux-gnu.so
charset_normalizer/md.cpython-311-aarch64-linux-gnu.so
charset_normalizer/md.cpython-311-aarch64-linux-musl.so
charset_normalizer/md.cpython-311-x86_64-linux-gnu.so
charset_normalizer/md.cpython-311-x86_64-linux-musl.so
charset_normalizer/md.cpython-312-aarch64-linux-gnu.so
charset_normalizer/md.cpython-312-aarch64-linux-musl.so
charset_normalizer/md.cpython-312-x86_64-linux-gnu.so
charset_normalizer/md.cpython-312-x86_64-linux-musl.so
charset_normalizer/md.cpython-313-aarch64-linux-gnu.so
charset_normalizer/md.cpython-313-aarch64-linux-musl.so
charset_normalizer/md.cpython-313-x86_64-linux-gnu.so
charset_normalizer/md.cpython-313-x86_64-linux-musl.so
charset_normalizer/md.cpython-314-aarch64-linux-gnu.so
charset_normalizer/md.cpython-314-aarch64-linux-musl.so
charset_normalizer/md.cpython-314-x86_64-linux-gnu.so
charset_normalizer/md.cpython-314-x86_64-linux-musl.so
charset_normalizer/md.cpython-39-aarch64-linux-gnu.so
charset_normalizer/md.cpython-39-x86_64-linux-gnu.so
charset_normalizer/md.py
charset_normalizer/md__mypyc.cpython-310-aarch64-linux-gnu.so
charset_normalizer/md__mypyc.cpython-310-x86_64-linux-gnu.so
charset_normalizer/md__mypyc.cpython-311-aarch64-linux-gnu.so
charset_normalizer/md__mypyc.cpython-311-aarch64-linux-musl.so
charset_normalizer/md__mypyc.cpython-311-x86_64-linux-gnu.so
charset_normalizer/md__mypyc.cpython-311-x86_64-linux-musl.so
charset_normalizer/md__mypyc.cpython-312-aarch64-linux-gnu.so
charset_normalizer/md__mypyc.cpython-312-aarch64-linux-musl.so
charset_normalizer/md__mypyc.cpython-312-x86_64-linux-gnu.so
contrast_agent_bundle-10.23.1.dist-info/licenses/LICENSE.txt
contrast_agent_bundle-10.23.1.dist-info/licenses/certifi/licenses/LICENSE
contrast_agent_bundle-10.23.1.dist-info/licenses/charset-normalizer/licenses/LICENSE
contrast_agent_bundle-10.23.1.dist-info/licenses/contrast-agent-lib/licenses/LICENSE.txt
contrast_agent_bundle-10.23.1.dist-info/licenses/contrast-fireball/licenses/LICENSE
contrast_agent_bundle-10.23.1.dist-info/licenses/idna/licenses/LICENSE.md
contrast_agent_bundle-10.23.1.dist-info/licenses/requests/licenses/LICENSE
contrast_agent_bundle-10.23.1.dist-info/licenses/urllib3/licenses/LICENSE.txt
contrast_agent_bundle-10.23.1.dist-info/METADATA
contrast_agent_bundle-10.23.1.dist-info/WHEEL
contrast_agent_bundle-10.23.1.dist-info/entry_points.txt
contrast_agent_bundle-10.23.1.dist-info/top_level.txt
contrast_agent_bundle-10.23.1.dist-info/RECORD
