Metadata-Version: 2.4
Name: contrast-agent-bundle
Version: 10.23.1
Summary: Contrast Security's agent for Python web frameworks
Author-email: "Contrast Security, Inc." <python@contrastsecurity.com>
License-Expression: LicenseRef-ContrastSecurity-ContrastPlatformLicense
Project-URL: Contrast, https://www.contrastsecurity.com
Project-URL: Change Log,
Project-URL: Support, https://support.contrastsecurity.com
Project-URL: Trouble Shooting,
Project-URL: Wiki, https://docs.contrastsecurity.com/
Keywords: security development
Classifier: Development Status :: 5 - Production/Stable
Classifier: Intended Audience :: Developers
Classifier: Programming Language :: Python :: 3
Requires-Python: >=3.9
License-File: LICENSE.txt
Provides-Extra: debug
Dynamic: license-file
Provides-Dist: contrast-agent-bundle==10.23.1
Provides-Dist: certifi==2026.1.4
Provides-Dist: urllib3==2.6.3
Provides-Dist: contrast-agent-lib==0.12.0
Provides-Dist: idna==3.11
Provides-Dist: contrast-fireball==0.1.22
Provides-Dist: charset-normalizer==3.4.4
Provides-Dist: requests==2.32.5
